wolphin_driver/__init__.py
wolphin_driver/__main__.py
wolphin_driver/main.py
wolphin_driver/server.py
wolphin_driver/settings.py
wolphin_driver/wsgi.py
wolphin_driver-0.0.4.dist-info/LICENSE
wolphin_driver-0.0.4.dist-info/METADATA
wolphin_driver-0.0.4.dist-info/WHEEL
wolphin_driver-0.0.4.dist-info/entry_points.txt
wolphin_driver-0.0.4.dist-info/top_level.txt
wolphin_driver-0.0.4.dist-info/RECORD
